[{"senderKeyId":1877502809,"senderChainKey":{"iteration":341,"seed":"kS9LvmZiSRHnGYQ7ej5ssoiCcvLCL8WjLAknleKEx4g="},"senderSigningKey":{"public":"BRlUeMYBpEjPD5R8SBfUvX3zhG4FBETsTEi4/KQDHpQr"},"senderMessageKeys":[{"iteration":161,"seed":"u+8x3eWpb2JR5inE+LKZk28cMzZeSq+tKz0czPxx3fs="},{},{},{},{},{},{},{},{},{},{},{},{},{},{},{},{},{},{},{},{},{},{},{},{},{},{},{},{},{},{},{},{},{},{},{},{},{},{},{},{},{},{},{},{},{},{},{},{},{},{},{},{},{},{},{},{},{},{},{},{},{},{},{},{},{},{},{},{},{},{},{},{},{},{},{},{},{},{},{},{},{},{},{},{},{},{},{},{},{},{},{},{},{},{},{},{},{},{},{},{},{},{},{},{},{},{},{},{},{},{},{},{},{},{},{},{},{},{},{},{},{},{},{},{},{},{},{},{},{}]},{"senderKeyId":1877502809,"senderChainKey":{"iteration":241,"seed":"wWok5VxnCUOuYlIaQw9InvB8rlbEpSRRJkvJerpxtRc="},"senderSigningKey":{"public":"BRlUeMYBpEjPD5R8SBfUvX3zhG4FBETsTEi4/KQDHpQr"},"senderMessageKeys":[]},{"senderKeyId":1877502809,"senderChainKey":{"iteration":253,"seed":"NGpKCh+R/UjhCXTDOA++F9SWVEwmtJczRx3GuQ+2SgI="},"senderSigningKey":{"public":"BRlUeMYBpEjPD5R8SBfUvX3zhG4FBETsTEi4/KQDHpQr"},"senderMessageKeys":[]},{"senderKeyId":1877502809,"senderChainKey":{"iteration":329,"seed":"rwkXhVAuag8p8EBj1MTEY4vPIRirbLkgGV9lzJ9hEVE="},"senderSigningKey":{"public":"BRlUeMYBpEjPD5R8SBfUvX3zhG4FBETsTEi4/KQDHpQr"},"senderMessageKeys":[]}]